README
setup.py
src/ddf/__init__.py
src/ddf/action.py
src/ddf/base.py
src/ddf/condition.py
src/ddf/form.py
src/ddf/rule.py
src/ddf/shortcuts.py
src/ddf.egg-info/PKG-INFO
src/ddf.egg-info/SOURCES.txt
src/ddf.egg-info/dependency_links.txt
src/ddf.egg-info/not-zip-safe
src/ddf.egg-info/top_level.txt