Metadata-Version: 1.1
Name: ddf
Version: 0.0.0
Summary: Dynamic forms for Django
Home-page: http://django-dynamic-form.rtfd.org
Author: James Pic
Author-email: jpic@yourlabs.org
License: UNKNOWN
Keywords: django dynamic form
Platform: UNKNOWN
Classifier: Development Status :: 1 - Planning
Classifier: Environment :: Web Environment
Classifier: Framework :: Django
Classifier: Intended Audience :: Developers
Classifier: License :: OSI Approved :: MIT License
Classifier: Operating System :: OS Independent
Classifier: Programming Language :: Python
Classifier: Programming Language :: Python :: 2
Classifier: Programming Language :: Python :: 3
Classifier: Topic :: Internet :: WWW/HTTP
Classifier: Topic :: Software Development :: Libraries :: Python Modules
